miarec_s3fs/__init__.py
miarec_s3fs/_version.txt
miarec_s3fs/errors.py
miarec_s3fs/helpers.py
miarec_s3fs/s3file.py
miarec_s3fs/s3fs.py
miarec_s3fs-2025.3.25.dist-info/licenses/LICENSE
miarec_s3fs-2025.3.25.dist-info/METADATA
miarec_s3fs-2025.3.25.dist-info/WHEEL
miarec_s3fs-2025.3.25.dist-info/top_level.txt
miarec_s3fs-2025.3.25.dist-info/zip-safe
miarec_s3fs-2025.3.25.dist-info/RECORD
