Metadata-Version: 2.4
Name: miarec_s3fs
Version: 2025.3.25
Summary: Amazon S3 filesystem for PyFilesystem2
Home-page: https://github.com/miarec/miarec_s3fs
Author: MiaRec
Author-email: support@miarec.com
License: MIT
Project-URL: Bug Tracker, https://github.com/miarec/miarec_s3fs/issues
Project-URL: Builds, https://github.com/miarec/miarec_s3fs/actions
Keywords: filesystem,Pyfilesystem2,s3,Amazon
Platform: any
Classifier: Development Status :: 5 - Production/Stable
Classifier: Intended Audience :: Developers
Classifier: License :: OSI Approved :: MIT License
Classifier: Operating System :: OS Independent
Classifier: Programming Language :: Python
Classifier: Programming Language :: Python :: 3.6
Classifier: Programming Language :: Python :: 3.7
Classifier: Programming Language :: Python :: 3.8
Classifier: Programming Language :: Python :: 3.9
Classifier: Programming Language :: Python :: 3.10
Classifier: Programming Language :: Python :: 3.11
Classifier: Topic :: System :: Filesystems
Requires-Python: >=3.6
License-File: LICENSE
Requires-Dist: fs~=2.4
Requires-Dist: boto3~=1.9
Requires-Dist: setuptools>=38.3.0
Provides-Extra: test
Requires-Dist: moto[s3]~=5.1; extra == "test"
Requires-Dist: pytest~=8.3; extra == "test"
Requires-Dist: pytest-cov~=6.0; extra == "test"
Dynamic: license-file
